beatbox_recorder/__init__.py
beatbox_recorder/core.py
beatbox_recorder-1.1.0.dist-info/LICENSE
beatbox_recorder-1.1.0.dist-info/METADATA
beatbox_recorder-1.1.0.dist-info/WHEEL
beatbox_recorder-1.1.0.dist-info/RECORD
