Metadata-Version: 2.3
Name: beatbox-recorder
Version: 1.1.0
Summary: Record and playback function calls for testing and mocking
License: MIT
Keywords: testing,mocking,recorder,playback
Author: Andrew Lewin
Requires-Python: >=3.9,<4.0
Classifier: Development Status :: 5 - Production/Stable
Classifier: Intended Audience :: Developers
Classifier: License :: OSI Approved :: MIT License
Classifier: Programming Language :: Python :: 3
Classifier: Programming Language :: Python :: 3.9
Classifier: Programming Language :: Python :: 3.10
Classifier: Programming Language :: Python :: 3.11
Classifier: Programming Language :: Python :: 3.12
Classifier: Programming Language :: Python :: 3.13
Classifier: Topic :: Software Development :: Libraries :: Python Modules
Classifier: Topic :: Software Development :: Testing
Project-URL: Homepage, https://github.com/andrewlwn77/beatbox-recorder-py
Project-URL: Repository, https://github.com/andrewlwn77/beatbox-recorder-py
